mega_rag-0.0.0.dist-info/licenses/LICENSE
megarag/__init__.py
megarag/version.py
mega_rag-0.0.0.dist-info/METADATA
mega_rag-0.0.0.dist-info/WHEEL
mega_rag-0.0.0.dist-info/entry_points.txt
mega_rag-0.0.0.dist-info/top_level.txt
mega_rag-0.0.0.dist-info/RECORD
